fast_model_server/__init__.py
fast_model_server/application.py
fast_model_server/common.py
fast_model_server/create.py
fast_model_server/main.py
fast_model_server/router_service.py
fast_model_server/template/router/common.py.template
fast_model_server/template/router/router.py.template
fast_model_server/template/router/service.py.template
fast_model_server/template/server/Dockerfile.template
fast_model_server/template/server/server.py.template
fast_model_server/template/server/start.sh.template
fast_model_server/template/server/stop.sh.template
fast_model_server/template/web/web.template
fast_model_server/utils/__init__.py
fast_model_server/utils/redis_cache.py
fast_model_server/utils/redis_connection.py
fast_model_server/utils/redis_lock.py
fast_model_server/utils/redis_msg_queue.py
fast_model_server/utils/bdcrawler/__init__.py
fast_model_server/utils/bdcrawler/crawler.config.json
fast_model_server/utils/bdcrawler/crawler.py
fast_model_server/utils/model_access/__init__.py
fast_model_server/utils/model_access/model_access.py
fast_model_server/utils/model_manage/__init__.py
fast_model_server/utils/model_manage/model_manage.config.json
fast_model_server/utils/model_manage/model_manage.py
fast_model_server/utils/model_manage/pack.sh
fast_model_server/utils/rule/__init__.py
fast_model_server/utils/rule/rule.py
fast_model_server/utils/rule/test/__init__.py
fast_model_server/utils/rule/test/test_rule.py
fast_model_server-1.2.1.0.dist-info/METADATA
fast_model_server-1.2.1.0.dist-info/WHEEL
fast_model_server-1.2.1.0.dist-info/top_level.txt
fast_model_server-1.2.1.0.dist-info/RECORD
