Metadata-Version: 2.1
Name: fast-model-server
Version: 1.2.1.0
Summary: python基础服务框架
Home-page: https://codeup.aliyun.com/64650c96168f0a5963451dec/lib/fast-model-server/blob/master/README.md
Author: yes_bobo
Author-email: fb_linux@163.com
License: MIT
Classifier: Programming Language :: Python
Classifier: Programming Language :: Python :: 3
Classifier: Programming Language :: Python :: 3.8
Requires-Dist: fastapi (>=0.63.0)
Requires-Dist: uvicorn (>=0.15.0)
Requires-Dist: pydantic (>=1.8.2)
Requires-Dist: typing (>=3.7.4.3)
Requires-Dist: aiofiles (>=0.8.0)
Requires-Dist: rule-engine (>=3.5.0)
Requires-Dist: dash (>=2.7.1)
Requires-Dist: bce-python-sdk
Requires-Dist: httpx
Requires-Dist: tqdm
Requires-Dist: redis
Requires-Dist: networkx
